./PKG-INFO
./README.md
./pyproject.toml
./server.py
./document/index.md
./document/team-fullstack.txt
./document/agents/analyst.txt
./document/agents/architect.txt
./document/agents/bmad-master.txt
./document/agents/bmad-orchestrator.txt
./document/agents/dev.txt
./document/agents/pm.txt
./document/agents/po.txt
./document/agents/qa.txt
./document/agents/sm.txt
./document/agents/ux-expert.txt
bmad_simple_mcp-0.2.0.dist-info/METADATA
bmad_simple_mcp-0.2.0.dist-info/WHEEL
bmad_simple_mcp-0.2.0.dist-info/entry_points.txt
bmad_simple_mcp-0.2.0.dist-info/RECORD
