Metadata-Version: 2.4
Name: bmad-simple-mcp
Version: 0.2.0
Summary: BMad Simple MCP - A lightweight MCP server for BMad Agent Documentation
Project-URL: Homepage, https://github.com/bmad-team/bmad-simple-mcp
Project-URL: Repository, https://github.com/bmad-team/bmad-simple-mcp
Project-URL: Issues, https://github.com/bmad-team/bmad-simple-mcp/issues
Author: BMad Team
License: MIT
Classifier: Development Status :: 4 - Beta
Classifier: Intended Audience :: Developers
Classifier: License :: OSI Approved :: MIT License
Classifier: Programming Language :: Python :: 3
Classifier: Programming Language :: Python :: 3.10
Classifier: Programming Language :: Python :: 3.11
Classifier: Programming Language :: Python :: 3.12
Requires-Python: >=3.10
Requires-Dist: anyio>=4.0.0
Requires-Dist: fastapi>=0.104.0
Requires-Dist: mcp>=1.0.0
Requires-Dist: pydantic>=2.0.0
Requires-Dist: sse-starlette>=1.6.0
Requires-Dist: starlette>=0.27.0
Requires-Dist: uvicorn>=0.24.0
Provides-Extra: dev
Requires-Dist: aiohttp>=3.8.0; extra == 'dev'
Requires-Dist: pytest-asyncio>=0.21.0; extra == 'dev'
Requires-Dist: pytest>=7.0.0; extra == 'dev'
